README.md
setup.py
xmlui/__init__.py
xmlui/xml_tk.py
xmlui/xml_ui_tool.py
xmlui/xml_wx.py
xmlui/xmlui.py
xmlui.egg-info/PKG-INFO
xmlui.egg-info/SOURCES.txt
xmlui.egg-info/dependency_links.txt
xmlui.egg-info/requires.txt
xmlui.egg-info/top_level.txt
xmlui/sample/__init__.py
xmlui/sample/wx_boxsize.py
xmlui/sample/wx_defaultlayout.py
xmlui/sample/wx_menu.py
xmlui/sample/wx_multiwindow.py
xmlui/sample/wx_simple.py