Metadata-Version: 1.0
Name: xmlui
Version: 0.9.0
Summary: 基于wxPython,使用xml描述ui结构的二次开发库
Home-page: https://gitee.com/zhangdianwei/xmlui.git
Author: zhang
Author-email: 2317365219@qq.com
License: MIT Licence
Keywords: pip,wx,xml
Platform: any
